{
  "timestamp": "2026-02-16 21:37:43 GMT",
  "eventName": "2026 Genesis",
  "bookmakers": ["BOYLESPORTS", "LADBROKES", "PADDY_POWER", "SKYBET"],
  "opportunities": [
    {
      "player": "J.J. Spaun",
      "bookmaker": "LADBROKES",
      "bmWinOdds": "55/1",
      "bmWin": 56.00,
      "bmPlace": 12.00,
      "bfWin": 90.00,
      "bfPlace": 8.00,
      "winEdge": -37.78,
      "placeEdge": 50.00,
      "edge": 6.11,
      "places": 8
    },
    {
      "player": "Scottie Scheffler",
      "bookmaker": "PADDY_POWER",
      "bmWinOdds": "3/1",
      "bmWin": 4.00,
      "bmPlace": 1.60,
      "bfWin": 4.70,
      "bfPlace": 1.39,
      "winEdge": -14.89,
      "placeEdge": 15.11,
      "edge": 0.11,
      "places": 10
    },
    {
      "player": "Scottie Scheffler",
      "bookmaker": "SKYBET",
      "bmWinOdds": "3/1",
      "bmWin": 4.00,
      "bmPlace": 1.60,
      "bfWin": 4.70,
      "bfPlace": 1.39,
      "winEdge": -14.89,
      "placeEdge": 15.11,
      "edge": 0.11,
      "places": 10
    },
    {
      "player": "Tommy Fleetwood",
      "bookmaker": "PADDY_POWER",
      "bmWinOdds": "16/1",
      "bmWin": 17.00,
      "bmPlace": 4.20,
      "bfWin": 26.00,
      "bfPlace": 3.20,
      "winEdge": -34.62,
      "placeEdge": 31.25,
      "edge": -1.68,
      "places": 10
    },
    {
      "player": "Tommy Fleetwood",
      "bookmaker": "BOYLESPORTS",
      "bmWinOdds": "16/1",
      "bmWin": 17.00,
      "bmPlace": 4.20,
      "bfWin": 26.00,
      "bfPlace": 3.20,
      "winEdge": -34.62,
      "placeEdge": 31.25,
      "edge": -1.68,
      "places": 10
    },
    {
      "player": "Tommy Fleetwood",
      "bookmaker": "SKYBET",
      "bmWinOdds": "16/1",
      "bmWin": 17.00,
      "bmPlace": 4.20,
      "bfWin": 26.00,
      "bfPlace": 3.20,
      "winEdge": -34.62,
      "placeEdge": 31.25,
      "edge": -1.68,
      "places": 10
    },
    {
      "player": "J.J. Spaun",
      "bookmaker": "PADDY_POWER",
      "bmWinOdds": "50/1",
      "bmWin": 51.00,
      "bmPlace": 11.00,
      "bfWin": 90.00,
      "bfPlace": 8.00,
      "winEdge": -43.33,
      "placeEdge": 37.50,
      "edge": -2.92,
      "places": 10
    },
    {
      "player": "J.J. Spaun",
      "bookmaker": "SKYBET",
      "bmWinOdds": "50/1",
      "bmWin": 51.00,
      "bmPlace": 11.00,
      "bfWin": 90.00,
      "bfPlace": 8.00,
      "winEdge": -43.33,
      "placeEdge": 37.50,
      "edge": -2.92,
      "places": 10
    },
    {
      "player": "Patrick Cantlay",
      "bookmaker": "PADDY_POWER",
      "bmWinOdds": "22/1",
      "bmWin": 23.00,
      "bmPlace": 5.40,
      "bfWin": 34.00,
      "bfPlace": 4.30,
      "winEdge": -32.35,
      "placeEdge": 25.58,
      "edge": -3.39,
      "places": 10
    },
    {
      "player": "Patrick Cantlay",
      "bookmaker": "SKYBET",
      "bmWinOdds": "22/1",
      "bmWin": 23.00,
      "bmPlace": 5.40,
      "bfWin": 34.00,
      "bfPlace": 4.30,
      "winEdge": -32.35,
      "placeEdge": 25.58,
      "edge": -3.39,
      "places": 10
    },
    {
      "player": "Scottie Scheffler",
      "bookmaker": "BOYLESPORTS",
      "bmWinOdds": "14/5",
      "bmWin": 3.80,
      "bmPlace": 1.56,
      "bfWin": 4.70,
      "bfPlace": 1.39,
      "winEdge": -19.15,
      "placeEdge": 12.23,
      "edge": -3.46,
      "places": 10
    },
    {
      "player": "Hideki Matsuyama",
      "bookmaker": "PADDY_POWER",
      "bmWinOdds": "20/1",
      "bmWin": 21.00,
      "bmPlace": 5.00,
      "bfWin": 30.00,
      "bfPlace": 4.30,
      "winEdge": -30.00,
      "placeEdge": 16.28,
      "edge": -6.86,
      "places": 10
    },
    {
      "player": "Hideki Matsuyama",
      "bookmaker": "SKYBET",
      "bmWinOdds": "20/1",
      "bmWin": 21.00,
      "bmPlace": 5.00,
      "bfWin": 30.00,
      "bfPlace": 4.30,
      "winEdge": -30.00,
      "placeEdge": 16.28,
      "edge": -6.86,
      "places": 10
    },
    {
      "player": "Ryo Hisatsune",
      "bookmaker": "PADDY_POWER",
      "bmWinOdds": "80/1",
      "bmWin": 81.00,
      "bmPlace": 17.00,
      "bfWin": 160.00,
      "bfPlace": 13.00,
      "winEdge": -49.38,
      "placeEdge": 30.77,
      "edge": -9.30,
      "places": 10
    },
    {
      "player": "Ryo Hisatsune",
      "bookmaker": "SKYBET",
      "bmWinOdds": "80/1",
      "bmWin": 81.00,
      "bmPlace": 17.00,
      "bfWin": 160.00,
      "bfPlace": 13.00,
      "winEdge": -49.38,
      "placeEdge": 30.77,
      "edge": -9.30,
      "places": 10
    },
    {
      "player": "Patrick Cantlay",
      "bookmaker": "BOYLESPORTS",
      "bmWinOdds": "20/1",
      "bmWin": 21.00,
      "bmPlace": 5.00,
      "bfWin": 34.00,
      "bfPlace": 4.30,
      "winEdge": -38.24,
      "placeEdge": 16.28,
      "edge": -10.98,
      "places": 10
    },
    {
      "player": "Rory McIlroy",
      "bookmaker": "PADDY_POWER",
      "bmWinOdds": "10/1",
      "bmWin": 11.00,
      "bmPlace": 3.00,
      "bfWin": 16.00,
      "bfPlace": 2.76,
      "winEdge": -31.25,
      "placeEdge": 8.70,
      "edge": -11.28,
      "places": 10
    },
    {
      "player": "Rory McIlroy",
      "bookmaker": "SKYBET",
      "bmWinOdds": "10/1",
      "bmWin": 11.00,
      "bmPlace": 3.00,
      "bfWin": 16.00,
      "bfPlace": 2.76,
      "winEdge": -31.25,
      "placeEdge": 8.70,
      "edge": -11.28,
      "places": 10
    },
    {
      "player": "Scottie Scheffler",
      "bookmaker": "LADBROKES",
      "bmWinOdds": "11/4",
      "bmWin": 3.75,
      "bmPlace": 1.55,
      "bfWin": 4.70,
      "bfPlace": 1.60,
      "winEdge": -20.21,
      "placeEdge": -3.29,
      "edge": -11.75,
      "places": 8
    },
    {
      "player": "Rory McIlroy",
      "bookmaker": "LADBROKES",
      "bmWinOdds": "12/1",
      "bmWin": 13.00,
      "bmPlace": 3.40,
      "bfWin": 16.00,
      "bfPlace": 3.62,
      "winEdge": -18.75,
      "placeEdge": -6.09,
      "edge": -12.42,
      "places": 8
    },
    {
      "player": "Tommy Fleetwood",
      "bookmaker": "LADBROKES",
      "bmWinOdds": "16/1",
      "bmWin": 17.00,
      "bmPlace": 4.20,
      "bfWin": 26.00,
      "bfPlace": 3.88,
      "winEdge": -34.62,
      "placeEdge": 8.22,
      "edge": -13.20,
      "places": 8
    },
    {
      "player": "Ludvig Aberg",
      "bookmaker": "LADBROKES",
      "bmWinOdds": "30/1",
      "bmWin": 31.00,
      "bmPlace": 7.00,
      "bfWin": 75.00,
      "bfPlace": 5.40,
      "winEdge": -58.67,
      "placeEdge": 29.63,
      "edge": -14.52,
      "places": 8
    },
    {
      "player": "Ryo Hisatsune",
      "bookmaker": "LADBROKES",
      "bmWinOdds": "75/1",
      "bmWin": 76.00,
      "bmPlace": 16.00,
      "bfWin": 160.00,
      "bfPlace": 13.00,
      "winEdge": -52.50,
      "placeEdge": 23.08,
      "edge": -14.71,
      "places": 8
    },
    {
      "player": "Patrick Cantlay",
      "bookmaker": "LADBROKES",
      "bmWinOdds": "22/1",
      "bmWin": 23.00,
      "bmPlace": 5.40,
      "bfWin": 34.00,
      "bfPlace": 5.44,
      "winEdge": -32.35,
      "placeEdge": -0.65,
      "edge": -16.50,
      "places": 8
    },
    {
      "player": "Xander Schauffele",
      "bookmaker": "PADDY_POWER",
      "bmWinOdds": "18/1",
      "bmWin": 19.00,
      "bmPlace": 4.60,
      "bfWin": 25.00,
      "bfPlace": 5.30,
      "winEdge": -24.00,
      "placeEdge": -13.21,
      "edge": -18.60,
      "places": 10
    },
    {
      "player": "Xander Schauffele",
      "bookmaker": "SKYBET",
      "bmWinOdds": "18/1",
      "bmWin": 19.00,
      "bmPlace": 4.60,
      "bfWin": 25.00,
      "bfPlace": 5.30,
      "winEdge": -24.00,
      "placeEdge": -13.21,
      "edge": -18.60,
      "places": 10
    },
    {
      "player": "Sam Burns",
      "bookmaker": "PADDY_POWER",
      "bmWinOdds": "25/1",
      "bmWin": 26.00,
      "bmPlace": 6.00,
      "bfWin": 50.00,
      "bfPlace": 5.80,
      "winEdge": -48.00,
      "placeEdge": 3.45,
      "edge": -22.28,
      "places": 10
    },
    {
      "player": "Sam Burns",
      "bookmaker": "SKYBET",
      "bmWinOdds": "25/1",
      "bmWin": 26.00,
      "bmPlace": 6.00,
      "bfWin": 50.00,
      "bfPlace": 5.80,
      "winEdge": -48.00,
      "placeEdge": 3.45,
      "edge": -22.28,
      "places": 10
    },
    {
      "player": "Hideki Matsuyama",
      "bookmaker": "BOYLESPORTS",
      "bmWinOdds": "16/1",
      "bmWin": 17.00,
      "bmPlace": 4.20,
      "bfWin": 30.00,
      "bfPlace": 4.30,
      "winEdge": -43.33,
      "placeEdge": -2.33,
      "edge": -22.83,
      "places": 10
    },
    {
      "player": "Jake Knapp",
      "bookmaker": "PADDY_POWER",
      "bmWinOdds": "30/1",
      "bmWin": 31.00,
      "bmPlace": 7.00,
      "bfWin": 60.00,
      "bfPlace": 7.00,
      "winEdge": -48.33,
      "placeEdge": 0.00,
      "edge": -24.17,
      "places": 10
    },
    {
      "player": "Jake Knapp",
      "bookmaker": "SKYBET",
      "bmWinOdds": "30/1",
      "bmWin": 31.00,
      "bmPlace": 7.00,
      "bfWin": 60.00,
      "bfPlace": 7.00,
      "winEdge": -48.33,
      "placeEdge": 0.00,
      "edge": -24.17,
      "places": 10
    },
    {
      "player": "Jake Knapp",
      "bookmaker": "LADBROKES",
      "bmWinOdds": "30/1",
      "bmWin": 31.00,
      "bmPlace": 7.00,
      "bfWin": 60.00,
      "bfPlace": 7.00,
      "winEdge": -48.33,
      "placeEdge": 0.00,
      "edge": -24.17,
      "places": 8
    },
    {
      "player": "Ryo Hisatsune",
      "bookmaker": "BOYLESPORTS",
      "bmWinOdds": "66/1",
      "bmWin": 67.00,
      "bmPlace": 14.20,
      "bfWin": 160.00,
      "bfPlace": 13.00,
      "winEdge": -58.13,
      "placeEdge": 9.23,
      "edge": -24.45,
      "places": 10
    },
    {
      "player": "Sam Burns",
      "bookmaker": "LADBROKES",
      "bmWinOdds": "28/1",
      "bmWin": 29.00,
      "bmPlace": 6.60,
      "bfWin": 50.00,
      "bfPlace": 7.15,
      "winEdge": -42.00,
      "placeEdge": -7.72,
      "edge": -24.86,
      "places": 8
    },
    {
      "player": "Xander Schauffele",
      "bookmaker": "LADBROKES",
      "bmWinOdds": "18/1",
      "bmWin": 19.00,
      "bmPlace": 4.60,
      "bfWin": 25.00,
      "bfPlace": 6.49,
      "winEdge": -24.00,
      "placeEdge": -29.15,
      "edge": -26.57,
      "places": 8
    },
    {
      "player": "Sam Burns",
      "bookmaker": "BOYLESPORTS",
      "bmWinOdds": "22/1",
      "bmWin": 23.00,
      "bmPlace": 5.40,
      "bfWin": 50.00,
      "bfPlace": 5.80,
      "winEdge": -54.00,
      "placeEdge": -6.90,
      "edge": -30.45,
      "places": 10
    },
    {
      "player": "Collin Morikawa",
      "bookmaker": "PADDY_POWER",
      "bmWinOdds": "22/1",
      "bmWin": 23.00,
      "bmPlace": 5.40,
      "bfWin": 40.00,
      "bfPlace": 7.00,
      "winEdge": -42.50,
      "placeEdge": -22.86,
      "edge": -32.68,
      "places": 10
    },
    {
      "player": "Collin Morikawa",
      "bookmaker": "BOYLESPORTS",
      "bmWinOdds": "22/1",
      "bmWin": 23.00,
      "bmPlace": 5.40,
      "bfWin": 40.00,
      "bfPlace": 7.00,
      "winEdge": -42.50,
      "placeEdge": -22.86,
      "edge": -32.68,
      "places": 10
    },
    {
      "player": "Collin Morikawa",
      "bookmaker": "SKYBET",
      "bmWinOdds": "22/1",
      "bmWin": 23.00,
      "bmPlace": 5.40,
      "bfWin": 40.00,
      "bfPlace": 7.00,
      "winEdge": -42.50,
      "placeEdge": -22.86,
      "edge": -32.68,
      "places": 10
    },
    {
      "player": "Xander Schauffele",
      "bookmaker": "BOYLESPORTS",
      "bmWinOdds": "14/1",
      "bmWin": 15.00,
      "bmPlace": 3.80,
      "bfWin": 25.00,
      "bfPlace": 5.30,
      "winEdge": -40.00,
      "placeEdge": -28.30,
      "edge": -34.15,
      "places": 10
    },
    {
      "player": "Collin Morikawa",
      "bookmaker": "LADBROKES",
      "bmWinOdds": "22/1",
      "bmWin": 23.00,
      "bmPlace": 5.40,
      "bfWin": 40.00,
      "bfPlace": 7.50,
      "winEdge": -42.50,
      "placeEdge": -28.00,
      "edge": -35.25,
      "places": 8
    },
    {
      "player": "Jake Knapp",
      "bookmaker": "BOYLESPORTS",
      "bmWinOdds": "25/1",
      "bmWin": 26.00,
      "bmPlace": 6.00,
      "bfWin": 60.00,
      "bfPlace": 7.00,
      "winEdge": -56.67,
      "placeEdge": -14.29,
      "edge": -35.48,
      "places": 10
    },
    {
      "player": "Hideki Matsuyama",
      "bookmaker": "LADBROKES",
      "bmWinOdds": "18/1",
      "bmWin": 19.00,
      "bmPlace": 4.60,
      "bfWin": 30.00,
      "bfPlace": 7.13,
      "winEdge": -36.67,
      "placeEdge": -35.51,
      "edge": -36.09,
      "places": 8
    }
  ]
}